Django22ZhongwenWendang/README.md
Django22ZhongwenWendang/__init__.py
Django22ZhongwenWendang/__main__.py
Django22ZhongwenWendang/file.epub
Django22ZhongwenWendang/index.html
Django22ZhongwenWendang/css/__init__.py
Django22ZhongwenWendang/css/annotations.css
Django22ZhongwenWendang/css/main.css
Django22ZhongwenWendang/css/normalize.css
Django22ZhongwenWendang/css/popup.css
Django22ZhongwenWendang/font/__init__.py
Django22ZhongwenWendang/font/fontello.eot
Django22ZhongwenWendang/font/fontello.svg
Django22ZhongwenWendang/font/fontello.ttf
Django22ZhongwenWendang/font/fontello.woff
Django22ZhongwenWendang/img/__init__.py
Django22ZhongwenWendang/img/annotator-glyph-sprite.png
Django22ZhongwenWendang/img/annotator-icon-sprite.png
Django22ZhongwenWendang/img/apple-touch-icon.png
Django22ZhongwenWendang/img/cancelfullscreen.png
Django22ZhongwenWendang/img/close.png
Django22ZhongwenWendang/img/fullscreen.png
Django22ZhongwenWendang/img/loader.gif
Django22ZhongwenWendang/img/menu-icon.png
Django22ZhongwenWendang/img/save.png
Django22ZhongwenWendang/img/saved.png
Django22ZhongwenWendang/img/settings-s.png
Django22ZhongwenWendang/img/settings.png
Django22ZhongwenWendang/img/star.png
Django22ZhongwenWendang/js/__init__.py
Django22ZhongwenWendang/js/epub.js
Django22ZhongwenWendang/js/epub.min.js
Django22ZhongwenWendang/js/epub.min.map
Django22ZhongwenWendang/js/hooks.min.js
Django22ZhongwenWendang/js/hooks.min.map
Django22ZhongwenWendang/js/reader.js
Django22ZhongwenWendang/js/reader.js.map
Django22ZhongwenWendang/js/reader.min.js
Django22ZhongwenWendang/js/reader.min.map
Django22ZhongwenWendang/js/hooks/__init__.py
Django22ZhongwenWendang/js/hooks/extensions/__init__.py
Django22ZhongwenWendang/js/hooks/extensions/highlight.js
Django22ZhongwenWendang/js/libs/__init__.py
Django22ZhongwenWendang/js/libs/jquery.min.js
Django22ZhongwenWendang/js/libs/localforage.min.js
Django22ZhongwenWendang/js/libs/screenfull.js
Django22ZhongwenWendang/js/libs/screenfull.min.js
django_2_2_zhongwen_wendang-2024.3.4.0.dist-info/METADATA
django_2_2_zhongwen_wendang-2024.3.4.0.dist-info/WHEEL
django_2_2_zhongwen_wendang-2024.3.4.0.dist-info/entry_points.txt
django_2_2_zhongwen_wendang-2024.3.4.0.dist-info/top_level.txt
django_2_2_zhongwen_wendang-2024.3.4.0.dist-info/RECORD
